ezt/MANIFEST.in
ezt/__init__.py
ezt/build/__init__.py
ezt/build/dfmodel/__init__.py
ezt/build/dfmodel/merge.py
ezt/build/dfmodel/models.py
ezt/build/dfmodel/persist_delta.py
ezt/build/dfmodel/py_model.py
ezt/build/dfmodel/sources.py
ezt/build/process_model.py
ezt/build/run.py
ezt/build/sqlmodel/__init__.py
ezt/build/sqlmodel/base.py
ezt/build/sqlmodel/execute.py
ezt/build/sqlmodel/register_sources.py
ezt/include/__init__.py
ezt/include/macros/base_macros.sql
ezt/include/starter_project/.gitignore
ezt/include/starter_project/README.md
ezt/include/starter_project/__init__.py
ezt/include/starter_project/ezt_project.yml
ezt/include/starter_project/models/__init__.py
ezt/include/starter_project/models/models.yml
ezt/include/starter_project/models/my_example.py
ezt/include/starter_project/sources.yml
ezt/main_cli.py
ezt/util/__init__.py
ezt/util/config.py
ezt/util/exceptions.py
ezt/util/fs.py
ezt/util/helpers.py
ezt/util/logger.py
ezt/util/result.py
ezt/util/validator.py
ezt/util/yaml_schemas/ezt_project_schema.yml
ezt/util/yaml_schemas/ezt_sources_schema.yml
ez_transform-0.1.6.dist-info/entry_points.txt
ez_transform-0.1.6.dist-info/LICENSE
ez_transform-0.1.6.dist-info/WHEEL
ez_transform-0.1.6.dist-info/METADATA
ez_transform-0.1.6.dist-info/RECORD
